gemlib/__init__.py
gemlib/conftest.py
gemlib/distributions/__init__.py
gemlib/distributions/brownian.py
gemlib/distributions/continuous_markov.py
gemlib/distributions/continuous_time_state_transition_model.py
gemlib/distributions/continuous_time_state_transition_model_test.py
gemlib/distributions/deterministic_state_transition_model.py
gemlib/distributions/deterministic_state_transition_model_test.py
gemlib/distributions/discrete_markov.py
gemlib/distributions/discrete_time_state_transition_model.py
gemlib/distributions/discrete_time_state_transition_model_test.py
gemlib/distributions/experimental/__init__.py
gemlib/distributions/experimental/discrete_approx_cont_state_transition_model.py
gemlib/distributions/experimental/state_transition_marginal_model.py
gemlib/distributions/hypergeometric.py
gemlib/distributions/hypergeometric_sampler.py
gemlib/distributions/hypergeometric_test.py
gemlib/distributions/kcategorical.py
gemlib/distributions/kcategorical_test.py
gemlib/distributions/uniform_integer.py
gemlib/distributions/uniform_integer_test.py
gemlib/func_util.py
gemlib/func_util_test.py
gemlib/mcmc/__init__.py
gemlib/mcmc/adaptive_hmc.py
gemlib/mcmc/adaptive_hmc_test.py
gemlib/mcmc/adaptive_random_walk_metropolis.py
gemlib/mcmc/adaptive_random_walk_metropolis_test.py
gemlib/mcmc/conftest.py
gemlib/mcmc/deprecated/__init__.py
gemlib/mcmc/deprecated/compound_kernel.py
gemlib/mcmc/deprecated/h5_posterior.py
gemlib/mcmc/deprecated/multi_scan_kernel.py
gemlib/mcmc/deprecated/zarr_posterior.py
gemlib/mcmc/discrete_time_state_transition_model/__init__.py
gemlib/mcmc/discrete_time_state_transition_model/conftest.py
gemlib/mcmc/discrete_time_state_transition_model/fixtures.py
gemlib/mcmc/discrete_time_state_transition_model/left_censored_events_impl.py
gemlib/mcmc/discrete_time_state_transition_model/left_censored_events_impl_test.py
gemlib/mcmc/discrete_time_state_transition_model/left_censored_events_mh.py
gemlib-0.13.1.dist-info/LICENSE
gemlib-0.13.1.dist-info/METADATA
gemlib-0.13.1.dist-info/WHEEL
gemlib-0.13.1.dist-info/RECORD
